{
  "resourceType": "Observation",
  "id": "07fc84e4-d989-4cac-8b2b-acf677b72482",
  "status": "final",
  "category": [
    {
      "coding": [
        {
          "system": "http://terminology.hl7.org/CodeSystem/observation-category",
          "code": "laboratory",
          "display": "Laboratory"
        }
      ]
    }
  ],
  "code": {
    "coding": [
      {
        "system": "http://loinc.org",
        "code": "718-7",
        "display": "Hemoglobin"
      }
    ],
    "text": "Hemoglobin"
  },
  "subject": {
    "reference": "Patient/1caa4b4a-c7f3-76b0-fe16-e04fc5a106f9"
  },
  "encounter": {
    "reference": "urn:uuid:501346e7-d082-4d68-bc50-4493d1aae28c"
  },
  "effectiveDateTime": "2025-11-14T00:00:00+00:00",
  "valueQuantity": {
    "value": 16.54,
    "unit": "g/dL",
    "system": "http://unitsofmeasure.org"
  }
}