{
  "resourceType": "Observation",
  "id": "d67355b4-367a-4984-a8ac-5cccbb6bc1c2",
  "status": "final",
  "category": [
    {
      "coding": [
        {
          "system": "http://terminology.hl7.org/CodeSystem/observation-category",
          "code": "laboratory",
          "display": "Laboratory"
        }
      ]
    }
  ],
  "code": {
    "coding": [
      {
        "system": "http://loinc.org",
        "code": "2947-0",
        "display": "Sodium"
      }
    ],
    "text": "Sodium"
  },
  "subject": {
    "reference": "Patient/8703e9b1-34f3-748d-0291-6e070e332243"
  },
  "encounter": {
    "reference": "urn:uuid:eb0b83e2-9799-43bb-9648-ba4f166efd97"
  },
  "effectiveDateTime": "2025-12-10T00:00:00+00:00",
  "valueQuantity": {
    "value": 143.87,
    "unit": "mmol/L",
    "system": "http://unitsofmeasure.org"
  }
}