{
  "resourceType": "Patient",
  "id": "9b8a9da0-4c66-f703-02c0-cf55279ca489",
  "meta": {
    "profile": [
      "http://hl7.org/fhir/us/core/StructureDefinition/us-core-patient"
    ],
    "tag": [
      {
        "system": "http://docgemma.dev/specialty",
        "code": "cv_surgery",
        "display": "Cardiovascular Surgery"
      }
    ]
  },
  "text": {
    "status": "generated",
    "div": "<div xmlns=\"http://www.w3.org/1999/xhtml\">Generated by <a href=\"https://github.com/synthetichealth/synthea\">Synthea</a>.Version identifier: master-branch-latest-10-g3e6dd1097\n .   Person seed: -7238800139242506493  Population seed: 1770500321071</div>"
  },
  "extension": [
    {
      "url": "http://hl7.org/fhir/us/core/StructureDefinition/us-core-race",
      "extension": [
        {
          "url": "ombCategory",
          "valueCoding": {
            "system": "urn:oid:2.16.840.1.113883.6.238",
            "code": "2106-3",
            "display": "White"
          }
        },
        {
          "url": "text",
          "valueString": "White"
        }
      ]
    },
    {
      "url": "http://hl7.org/fhir/us/core/StructureDefinition/us-core-ethnicity",
      "extension": [
        {
          "url": "ombCategory",
          "valueCoding": {
            "system": "urn:oid:2.16.840.1.113883.6.238",
            "code": "2186-5",
            "display": "Not Hispanic or Latino"
          }
        },
        {
          "url": "text",
          "valueString": "Not Hispanic or Latino"
        }
      ]
    },
    {
      "url": "http://hl7.org/fhir/StructureDefinition/patient-mothersMaidenName",
      "valueString": "Clarence5 Rempel203"
    },
    {
      "url": "http://hl7.org/fhir/us/core/StructureDefinition/us-core-birthsex",
      "valueCode": "M"
    },
    {
      "url": "http://hl7.org/fhir/StructureDefinition/patient-birthPlace",
      "valueAddress": {
        "city": "Wellesley",
        "state": "Massachusetts",
        "country": "US"
      }
    },
    {
      "url": "http://synthetichealth.github.io/synthea/disability-adjusted-life-years",
      "valueDecimal": 0.0
    },
    {
      "url": "http://synthetichealth.github.io/synthea/quality-adjusted-life-years",
      "valueDecimal": 55.0
    }
  ],
  "identifier": [
    {
      "system": "https://github.com/synthetichealth/synthea",
      "value": "9b8a9da0-4c66-f703-02c0-cf55279ca489"
    },
    {
      "type": {
        "coding": [
          {
            "system": "http://terminology.hl7.org/CodeSystem/v2-0203",
            "code": "MR",
            "display": "Medical Record Number"
          }
        ],
        "text": "Medical Record Number"
      },
      "system": "http://hospital.smarthealthit.org",
      "value": "9b8a9da0-4c66-f703-02c0-cf55279ca489"
    },
    {
      "type": {
        "coding": [
          {
            "system": "http://terminology.hl7.org/CodeSystem/v2-0203",
            "code": "SS",
            "display": "Social Security Number"
          }
        ],
        "text": "Social Security Number"
      },
      "system": "http://hl7.org/fhir/sid/us-ssn",
      "value": "999-96-5244"
    },
    {
      "type": {
        "coding": [
          {
            "system": "http://terminology.hl7.org/CodeSystem/v2-0203",
            "code": "DL",
            "display": "Driver's license number"
          }
        ],
        "text": "Driver's license number"
      },
      "system": "urn:oid:2.16.840.1.113883.4.3.25",
      "value": "S99935927"
    },
    {
      "type": {
        "coding": [
          {
            "system": "http://terminology.hl7.org/CodeSystem/v2-0203",
            "code": "PPN",
            "display": "Passport Number"
          }
        ],
        "text": "Passport Number"
      },
      "system": "http://hl7.org/fhir/sid/passport-USA",
      "value": "X48478168X"
    }
  ],
  "name": [
    {
      "use": "official",
      "family": "Bins636",
      "given": [
        "Hyman89"
      ],
      "prefix": [
        "Mr."
      ]
    }
  ],
  "telecom": [
    {
      "system": "phone",
      "value": "555-603-2299",
      "use": "home"
    }
  ],
  "gender": "male",
  "birthDate": "1970-10-29",
  "address": [
    {
      "extension": [
        {
          "url": "http://hl7.org/fhir/StructureDefinition/geolocation",
          "extension": [
            {
              "url": "latitude",
              "valueDecimal": 42.13011156398056
            },
            {
              "url": "longitude",
              "valueDecimal": -71.39890520292917
            }
          ]
        }
      ],
      "line": [
        "651 Romaguera Tunnel"
      ],
      "city": "Millis-Clicquot",
      "state": "MA",
      "postalCode": "00000",
      "country": "US"
    }
  ],
  "maritalStatus": {
    "coding": [
      {
        "system": "http://terminology.hl7.org/CodeSystem/v3-MaritalStatus",
        "code": "S",
        "display": "Never Married"
      }
    ],
    "text": "Never Married"
  },
  "multipleBirthInteger": 1,
  "communication": [
    {
      "language": {
        "coding": [
          {
            "system": "urn:ietf:bcp:47",
            "code": "en-US",
            "display": "English (United States)"
          }
        ],
        "text": "English (United States)"
      }
    }
  ]
}